Metadata-Version: 2.4
Name: clashy.py
Version: 25.12.5
Summary: A python wrapper for the Clash of Clans API
Author: ClashKing
Maintainer: MagicTheDev
License: MIT
Project-URL: documentation, https://clashy.clashk.ing/en/latest/
Project-URL: repository, https://github.com/ClashKingInc/clashy.py
Project-URL: changelog, https://clashy.clashk.ing/en/latest/miscellaneous/changelog.html
Keywords: coc,clash of clans,clashy.py,clash api
Classifier: Development Status :: 5 - Production/Stable
Classifier: Programming Language :: Python
Classifier: Programming Language :: Python :: 3.10
Classifier: Programming Language :: Python :: 3.11
Classifier: Programming Language :: Python :: 3.12
Classifier: Programming Language :: Python :: 3.13
Classifier: Programming Language :: Python :: 3.14
Classifier: Natural Language :: English
Classifier: Operating System :: OS Independent
Classifier: License :: OSI Approved :: MIT License
Classifier: Intended Audience :: Developers
Classifier: Topic :: Software Development :: Libraries :: Python Modules
Requires-Python: >=3.10.0
License-File: LICENSE
Requires-Dist: aiohttp
Requires-Dist: orjson
Provides-Extra: docs
Requires-Dist: sphinx; extra == "docs"
Requires-Dist: sphinx_rtd_theme; extra == "docs"
Requires-Dist: sphinxcontrib_trio; extra == "docs"
Requires-Dist: autodocsumm; extra == "docs"
Dynamic: license-file
